coschedule/__init__.py
coschedule-0.0.0.dist-info/LICENSE
coschedule-0.0.0.dist-info/METADATA
coschedule-0.0.0.dist-info/WHEEL
coschedule-0.0.0.dist-info/top_level.txt
coschedule-0.0.0.dist-info/RECORD
