Metadata-Version: 2.1
Name: coschedule
Version: 0.0.0
Summary: 联络：coalgo@shanshu.ai
Author: ['coalgo@shanshu.ai']
License-File: LICENSE
